PDFpy/PDFpy_main.py
PDFpy/__init__.py
PDFpy-0.0.35.dist-info/LICENSE.txt
PDFpy-0.0.35.dist-info/METADATA
PDFpy-0.0.35.dist-info/WHEEL
PDFpy-0.0.35.dist-info/top_level.txt
PDFpy-0.0.35.dist-info/RECORD
