Metadata-Version: 2.1
Name: PDFpy
Version: 0.0.35
Summary: Simple PDF editing made fast
Home-page: UNKNOWN
Author: JonasHri
Author-email: jonasharriehausen@gmail.com
License: MIT
Keywords: python,PDF,PDFpy
Platform: UNKNOWN
Classifier: Development Status :: 1 - Planning
Classifier: Intended Audience :: Developers
Classifier: Programming Language :: Python :: 3
Classifier: Operating System :: Unix
Classifier: Operating System :: MacOS :: MacOS X
Classifier: Operating System :: Microsoft :: Windows
Requires-Dist: PyPDF2
